iss_location_tracker-0.1.0.dist-info/licenses/LICENSE
iss_tracker/__init__.py
iss_tracker/tracker.py
tests/__init__.py
tests/test_tracker.py
iss_location_tracker-0.1.0.dist-info/METADATA
iss_location_tracker-0.1.0.dist-info/WHEEL
iss_location_tracker-0.1.0.dist-info/top_level.txt
iss_location_tracker-0.1.0.dist-info/RECORD
